hadar_dashboard/__init__.py
hadar_dashboard/dashboard.py
hadar_dashboard-0.4.0.dist-info/LICENSE
hadar_dashboard-0.4.0.dist-info/METADATA
hadar_dashboard-0.4.0.dist-info/WHEEL
hadar_dashboard-0.4.0.dist-info/top_level.txt
hadar_dashboard-0.4.0.dist-info/RECORD
