Metadata-Version: 2.1
Name: hadar-dashboard
Version: 0.4.0
Summary: jupyter dashboard to navigate into Hadar results
Home-page: https://github.com/hadar-simulator/jupyter-dashboard
Author: RTE France
Author-email: francois.jolain@rte-international.com
License: UNKNOWN
Platform: UNKNOWN
Classifier: Programming Language :: Python :: 3
Classifier: License :: OSI Approved :: Apache Software License
Classifier: Operating System :: OS Independent
Requires-Python: >=3.6
Requires-Dist: jupyter
Requires-Dist: plotly
Requires-Dist: hadar (==0.4.0)
